LICENSE
MANIFEST.in
README.rst
setup.cfg
setup.py
pyramid_logging/__init__.py
pyramid_logging.egg-info/PKG-INFO
pyramid_logging.egg-info/SOURCES.txt
pyramid_logging.egg-info/dependency_links.txt
pyramid_logging.egg-info/entry_points.txt
pyramid_logging.egg-info/not-zip-safe
pyramid_logging.egg-info/top_level.txt
tests/__init__.py
tests/test_logging.py