Metadata-Version: 1.1
Name: pyramid-logging
Version: 0.1
Summary: Advanced logger for pyramid
Home-page: https://github.com/LeResKP/pyramid_logging
Author: Aurélien Matouillot
Author-email: a.matouillot@gmail.com
License: MIT
Platform: UNKNOWN
Classifier: Framework :: Pyramid
Classifier: Topic :: Software Development :: Libraries :: Python Modules
Classifier: Topic :: System :: Logging
Classifier: Intended Audience :: Developers
Classifier: Operating System :: OS Independent
Classifier: Programming Language :: Python
Classifier: Programming Language :: Python :: 2.6
Classifier: Programming Language :: Python :: 2.7
Classifier: Topic :: Internet :: WWW/HTTP
